{
  "name": "Fanny Bates",
  "age": 48,
  "address": {
    "street": "Zescil Pike",
    "city": "Nipikruv",
    "state": "NJ",
    "zip": "87451"
  },
  "contact": {
    "phone": "(964) 257-6459",
    "servicePhone": "800659247"
  },
  "birthday": "1990-06-11T17:55:37.868Z",
  "ip": "172.175.129.209",
  "foo": "bar",
  "profile": {
    "about": "Fusmobu aw cavasca dufiwim detbohhiw tu fol jevjib olib judo zizof amiwusnuk bav pefgar zanse. Sigoha uno delvikmuv uk lop roromded ipadibuva digev wucozja hudeg lug agejug odiej. Jes bulwojaga tulimej pippos ji uwkifseh vabbeniro gavhu pele mapetas ema hu fe zi oz noc refca. Nupla gohhi jizpewgos honazad rohlojezi viac oczapju tehuda tijnu bimiz keho zin ej itimmi jenpitdut lekeet. Omovusor egu nih obo ra liirha litkecvar kugip onage bite giwkivu ohowotos hile tuz econpon ji. Den cotug zodon nav wufadwa jusomewa oko vozgiwo vuwsunji po nubumhup pu palku befehlo pabvu cucgam ed. Pobsir pom magpebe cofcis olu nub baze fibfacud dugajnud zic wa niutupev heguuz.",
    "bio": "Ufzul if sidowone osiko uvajew ale zom sefdil fipin figoc me licu catina. Bavelgar bimpip ilpat ite bookim or macu kow we bukruha se makgas tusuj becsuvhaz fetag. Ficerah ter za bubejti patda suokle recavbu saz voge woghoor magnafu oj fap ukewo."
  },
  "apiKey": "b6d301d552b31428a114198d12ee9394b7d443f777781c94d064e65e021e6278",
  "currency": {
    "code": "PEN",
    "name": "Peru Nuevo Sol"
  }
}