{
  "name": "Marian Terry",
  "age": 61,
  "address": {
    "street": "Ponlu Pass",
    "city": "Tijugov",
    "state": "CA",
    "zip": "89834"
  },
  "contact": {
    "phone": "(858) 928-9698",
    "servicePhone": "800975443"
  },
  "birthday": "1993-04-07T00:07:14.423Z",
  "ip": "86.219.1.43",
  "foo": "bar",
  "profile": {
    "about": "Vatakoda metne wutusec cumbah osa ebedauk jadlu zoddehku wejru lehubamiz zusigzab ruprejwan rosdow icjocfi buuh uwelikow vojarha. Gaez ba bamogzo ra rismiswe zepit omo natacaher oledaddi doru demsati du ca tippig ceze vurpab. Zabab ozgo vevto paukpo edietok kitvoja de ahe hew zubirut degzop vek agcoke gakga bic. Cujte purehowij curiraj gujlaiv eru tulopus zes ne ov of ba cir. Jisdegew keop eheto sedwedoj ipfev iko ufa uggakhal mufueji ker ubu misefnu ivibwaz dek da jufez riul ru. Agaaj eri fa gazponhag obpop mibaram jubpamwo hejcahwo da imsilcaj nejozowa voc ko ehilohe.",
    "bio": "Ca agunu famosac numehat sonudto satefi ovobot ni afhena uvuecipaw ro nuk voj venezadut leinpof talatuki. Tezili loaduum tek esekugaze si hoisva lir mor hudkegci ihsob venmih puzo gebinelo. Bewamuz sacomuak zignu utopde eduvcut jungihlac bon mojew vegvibfi viciz ge low lopven hag opik dumeghoc balu. Nutu nol wuhwuulu igouvgo hazpuwe demejez loloafu dun disunu anihajwiv zuvwe jazu tesep bumvuhup zu bokul lopuwwi."
  },
  "apiKey": "645d380fb59cf05af4fedad65d3cfe7c2fba2166aa1825dbb2528196ca626ffd",
  "currency": {
    "code": "WST",
    "name": "Samoa Tala"
  }
}